{   
    "SIZE_X": 7,
    "SIZE_Y": 5,
    "numObjectif": 1,
    "pasMinimum": 8,
    "hero":
        {"x": 1, "y": 2},
    "BlocObjectif": [
        {"x": 2, "y": 2, "id": 1}
    ],
    "CaseObjectif": [
        {"x": 2, "y": 1, "id": 1}
    ],
    "Bloc": [
    ],
    "Mur": [
        {"x": 1,"y": 0}, {"x": 2,"y": 0}, {"x": 3,"y": 0}, {"x": 3,"y": 0}, {"x": 4,"y": 0}, {"x": 5,"y": 0}, {"x": 6,"y": 0},
        {"x": 6,"y": 1}, {"x": 6,"y": 2}, {"x": 6,"y": 3}, {"x": 5,"y": 3}, {"x": 5,"y": 4}, {"x": 4,"y": 4}, {"x": 3,"y": 4},
        {"x": 2,"y": 4}, {"x": 2,"y": 3}, {"x": 1,"y": 3}, {"x": 0,"y": 3}, {"x": 0,"y": 2}, {"x": 0,"y": 1}, {"x": 1,"y": 1}
    ],
    "Piege": [
    ],
    "Glace": [
        {"x": 3, "y": 1}, {"x": 3, "y": 2}
    ],
    "Rail": [
    ]
}